HAT/__init__.py
HAT/__main__.py
HAT/binner.py
HAT/chi2theta.py
HAT/crystal.py
HAT/fileio.py
HAT/interface.py
HAT/plotting.py
HAT/scene3d.py
HAT/script.py
HAT/transformdet.py
HAT/util.py
HAT/icons/addmask.svg
HAT/icons/clearmask.svg
HAT/icons/extractroi.svg
HAT/icons/loadmask.svg
HAT/icons/loadroi.svg
HAT/icons/rockingscan.svg
HAT/icons/roi.svg
HAT/icons/savemask.svg
HAT/icons/saveroi.svg
xrayhat-2.0.4.dist-info/LICENSE
xrayhat-2.0.4.dist-info/METADATA
xrayhat-2.0.4.dist-info/WHEEL
xrayhat-2.0.4.dist-info/entry_points.txt
xrayhat-2.0.4.dist-info/top_level.txt
xrayhat-2.0.4.dist-info/RECORD
