Metadata-Version: 2.1
Name: xrayhat
Version: 2.0.4
Summary: Software for the analysis of high-energy surface x-ray diffraction data
Author-email: Gary Harlow <gsharlow@gmail.com>, Sebastian Pfaff <sebastian.pfaff@forbrf.lth.se>
License: MIT License        
Project-URL: homepage, https://github.com/gary-harlow/HESXRD-Analysis-Toolkit
Classifier: License :: OSI Approved :: MIT License
Classifier: Programming Language :: Python
Classifier: Programming Language :: Python :: 3
Requires-Python: >=3.8
License-File: LICENSE
Requires-Dist: PyQt6 (>=6.3.1)
Requires-Dist: pyqtgraph (>=0.12.4)
Requires-Dist: scipy (>=1.5.4)
Requires-Dist: numba (>=0.51.2)
Requires-Dist: numpy (>=1.19.3)
Requires-Dist: h5py (>=3.1.0)
Requires-Dist: hdf5plugin (>=2.3.1)
Requires-Dist: fabio (>=0.10.2)
Requires-Dist: natsort (>=8.1.0)
